{
  "version": "2.0.0",
  "lastFullUpdate": "2026-01-11T02:53:33.799Z",
  "lastIncrementalUpdate": "2026-01-13T16:11:25.994Z",
  "symbols": {
    "DNB": {
      "name": "DNB Bank ASA",
      "type": "EQS",
      "currency": "NOK",
      "lastUpdate": "2026-01-13T16:11:12.393Z",
      "hasQuote": true,
      "hasDividends": false,
      "dataQuality": "good"
    },
    "TEL": {
      "name": "Telenor ASA",
      "type": "EQS",
      "currency": "NOK",
      "lastUpdate": "2026-01-13T16:11:12.399Z",
      "hasQuote": true,
      "hasDividends": false,
      "dataQuality": "good"
    },
    "MOWI": {
      "name": "Mowi ASA",
      "type": "EQS",
      "currency": "NOK",
      "lastUpdate": "2026-01-13T16:11:12.385Z",
      "hasQuote": false,
      "hasDividends": false,
      "dataQuality": "stale"
    },
    "EQNR": {
      "name": "Equinor ASA",
      "type": "EQS",
      "currency": "NOK",
      "lastUpdate": "2026-01-13T16:11:12.454Z",
      "hasQuote": true,
      "hasDividends": false,
      "dataQuality": "good"
    },
    "YAR": {
      "name": "Yara International ASA",
      "type": "EQS",
      "currency": "NOK",
      "lastUpdate": "2026-01-13T16:11:12.387Z",
      "hasQuote": false,
      "hasDividends": false,
      "dataQuality": "stale"
    },
    "NHY": {
      "name": "Norsk Hydro ASA",
      "type": "EQS",
      "currency": "NOK",
      "lastUpdate": "2026-01-13T16:11:25.969Z",
      "hasQuote": false,
      "hasDividends": false,
      "dataQuality": "stale"
    },
    "SNTIA": {
      "name": "Sentia Group ASA",
      "type": "EQS",
      "currency": "NOK",
      "lastUpdate": "2026-01-13T16:11:25.959Z",
      "hasQuote": false,
      "hasDividends": false,
      "dataQuality": "stale"
    },
    "ORK": {
      "name": "Orkla ASA",
      "type": "EQS",
      "currency": "NOK",
      "lastUpdate": "2026-01-13T16:11:25.994Z",
      "hasQuote": false,
      "hasDividends": false,
      "dataQuality": "stale"
    },
    "SALM": {
      "name": "SalMar ASA",
      "type": "EQS",
      "currency": "NOK",
      "lastUpdate": "2026-01-13T16:11:25.770Z",
      "hasQuote": true,
      "hasDividends": false,
      "dataQuality": "good"
    }
  },
  "metadata": {
    "exchange": "Oslo Børs",
    "source": "Finnhub",
    "updateSchedule": "Pre-market and post-close on weekdays"
  }
}