{
  "version": "2.0.0",
  "lastFullUpdate": "2025-11-09T02:38:30.155Z",
  "lastIncrementalUpdate": "2025-11-11T16:09:00.598Z",
  "symbols": {
    "DNB": {
      "name": "DNB Bank ASA",
      "type": "EQS",
      "currency": "NOK",
      "lastUpdate": "2025-11-11T16:08:46.791Z",
      "hasQuote": true,
      "hasDividends": false,
      "dataQuality": "good"
    },
    "TEL": {
      "name": "Telenor ASA",
      "type": "EQS",
      "currency": "NOK",
      "lastUpdate": "2025-11-11T16:08:46.778Z",
      "hasQuote": true,
      "hasDividends": false,
      "dataQuality": "good"
    },
    "MOWI": {
      "name": "Mowi ASA",
      "type": "EQS",
      "currency": "NOK",
      "lastUpdate": "2025-11-11T16:08:46.940Z",
      "hasQuote": false,
      "hasDividends": false,
      "dataQuality": "stale"
    },
    "EQNR": {
      "name": "Equinor ASA",
      "type": "EQS",
      "currency": "NOK",
      "lastUpdate": "2025-11-11T16:08:46.694Z",
      "hasQuote": true,
      "hasDividends": false,
      "dataQuality": "good"
    },
    "YAR": {
      "name": "Yara International ASA",
      "type": "EQS",
      "currency": "NOK",
      "lastUpdate": "2025-11-11T16:08:46.806Z",
      "hasQuote": false,
      "hasDividends": false,
      "dataQuality": "stale"
    },
    "NHY": {
      "name": "Norsk Hydro ASA",
      "type": "EQS",
      "currency": "NOK",
      "lastUpdate": "2025-11-11T16:09:00.596Z",
      "hasQuote": false,
      "hasDividends": false,
      "dataQuality": "stale"
    },
    "SNTIA": {
      "name": "Sentia Group ASA",
      "type": "EQS",
      "currency": "NOK",
      "lastUpdate": "2025-11-11T16:09:00.584Z",
      "hasQuote": false,
      "hasDividends": false,
      "dataQuality": "stale"
    },
    "ORK": {
      "name": "Orkla ASA",
      "type": "EQS",
      "currency": "NOK",
      "lastUpdate": "2025-11-11T16:09:00.598Z",
      "hasQuote": false,
      "hasDividends": false,
      "dataQuality": "stale"
    },
    "SALM": {
      "name": "SalMar ASA",
      "type": "EQS",
      "currency": "NOK",
      "lastUpdate": "2025-11-11T16:09:00.594Z",
      "hasQuote": true,
      "hasDividends": false,
      "dataQuality": "good"
    }
  },
  "metadata": {
    "exchange": "Oslo Børs",
    "source": "Finnhub",
    "updateSchedule": "Pre-market and post-close on weekdays"
  }
}